pypiprivatizer/__init__.py
pypiprivatizer/__main__.py
pypiprivatizer-1.0.0.dist-info/METADATA
pypiprivatizer-1.0.0.dist-info/WHEEL
pypiprivatizer-1.0.0.dist-info/entry_points.txt
pypiprivatizer-1.0.0.dist-info/license_files/LICENSE.txt
pypiprivatizer-1.0.0.dist-info/RECORD
