Metadata-Version: 2.1
Name: pypiprivatizer
Version: 1.0.0
Summary: A python toolkit to download packages from PyPI and copy them in a directory compatible with the pip index.
Project-URL: Homepage, https://github.com/abulgher/pypiprivatizer
Author-email: Antonio Bulgheroni <antonio.bulgheroni@gmail.com>
License: Copyright (c) 2018 The Python Packaging Authority
Classifier: License :: OSI Approved :: MIT License
Classifier: Operating System :: OS Independent
Classifier: Programming Language :: Python :: 3
Requires-Python: >=3.9.7
